pyacm/__init__.py
pyacm/acm.py
pyacm-1.1.dist-info/licenses/LICENSE
pyacm-1.1.dist-info/METADATA
pyacm-1.1.dist-info/WHEEL
pyacm-1.1.dist-info/top_level.txt
pyacm-1.1.dist-info/RECORD
