Metadata-Version: 2.4
Name: pyacm
Version: 1.1
Summary: ACM Term Premium
Author: Tobias Adrian, Richard K. Crump, Emanuel Moench
Maintainer: Gustavo Amarante
Maintainer-email: developer@dsgepy.com
Keywords: asset pricing,yield curve,term premium
License-File: LICENSE
Requires-Dist: matplotlib
Requires-Dist: numpy
Requires-Dist: pandas
Requires-Dist: scikit-learn
Requires-Dist: statsmodels
Dynamic: author
Dynamic: description
Dynamic: description-content-type
Dynamic: keywords
Dynamic: license-file
Dynamic: maintainer
Dynamic: maintainer-email
Dynamic: requires-dist
Dynamic: summary
